clickmd/CHANGELOG.md
clickmd/README.md
clickmd/ROADMAP.md
clickmd/__init__.py
clickmd/clickmd.toon-schema.json
clickmd/decorators.py
clickmd/devtools.py
clickmd/help.py
clickmd/logger.py
clickmd/progress.py
clickmd/py.typed
clickmd/renderer.py
clickmd/rich_backend.py
clickmd/themes.py
clickmd/docs/API.md
clickmd/docs/CONTRIBUTING.md
clickmd/examples/api_response.py
clickmd/examples/basic.py
clickmd/examples/build_script.py
clickmd/examples/cli_app.py
clickmd/examples/cli_colors.py
clickmd/examples/colored_logging.py
clickmd/examples/config_viewer.py
clickmd/examples/custom_renderer.py
clickmd/examples/logger_usage.py
clickmd/examples/markdown_help.py
clickmd/examples/one_liners.py
clickmd/examples/phase1_features.py
clickmd/examples/phase3_progress.py
clickmd/examples/phase4_themes.py
clickmd/examples/phase5_devtools.py
clickmd/examples/quickstart.py
clickmd/examples/simple_cli.py
clickmd/examples_output/api_response.md
clickmd/examples_output/basic.md
clickmd/examples_output/cli_app.md
clickmd/examples_output/cli_colors.md
clickmd/examples_output/config_viewer.md
clickmd/examples_output/custom_renderer.md
clickmd/examples_output/logger_usage.md
clickmd/examples_output/logging.md
clickmd/examples_output/one_liners.md
clickmd/examples_output/quickstart.md
clickmd/examples_output/simple_cli_help.md
clickmd/examples_output/simple_cli_info.md
clickmd/tests/__init__.py
clickmd/tests/test_core.py
clickmd/tests/test_decorators.py
clickmd/tests/test_logger.py
clickmd/tests/test_renderer.py
clickmd/tools/md_to_html.py
clickmd/tools/test_examples_md.py
pycontracts/__init__.py
pycontracts/base.py
pycontracts/generate.py
pycontracts/generate_json.py
pycontracts/entities/__init__.py
pycontracts/entities/company.py
pycontracts/entities/contact.py
pycontracts/entities/deal.py
pycontracts/entities/project.py
pycontracts/entities/task.py
pycontracts/entities/user.py
pycontracts/examples/__init__.py
pycontracts/examples/booking_contract.py
pycontracts/examples/hr_contract.py
reclapp-2.2.1.dist-info/licenses/LICENSE
reclapp-2.2.1.dist-info/METADATA
reclapp-2.2.1.dist-info/WHEEL
reclapp-2.2.1.dist-info/entry_points.txt
reclapp-2.2.1.dist-info/top_level.txt
reclapp-2.2.1.dist-info/RECORD
