Metadata-Version: 2.4
Name: reclapp
Version: 2.2.1
Summary: AI-Native Declarative Platform for B2B Applications
Author-email: Reclapp Team <team@reclapp.dev>
License: Apache-2.0
Project-URL: Homepage, https://github.com/wronai/contract
Project-URL: Documentation, https://github.com/wronai/contract/docs
Project-URL: Repository, https://github.com/wronai/contract
Keywords: ai,code-generation,contracts,b2b,llm
Classifier: Development Status :: 4 - Beta
Classifier: Environment :: Console
Classifier: Intended Audience :: Developers
Classifier: License :: OSI Approved :: Apache Software License
Classifier: Operating System :: OS Independent
Classifier: Programming Language :: Python :: 3
Classifier: Programming Language :: Python :: 3.10
Classifier: Programming Language :: Python :: 3.11
Classifier: Programming Language :: Python :: 3.12
Classifier: Topic :: Software Development :: Code Generators
Requires-Python: >=3.10
License-File: LICENSE
Requires-Dist: pydantic>=2.5.0
Requires-Dist: click>=8.0.0
Requires-Dist: rich>=13.0.0
Requires-Dist: httpx>=0.25.0
Provides-Extra: dev
Requires-Dist: pytest>=7.0.0; extra == "dev"
Requires-Dist: pytest-asyncio>=0.21.0; extra == "dev"
Requires-Dist: black>=23.0.0; extra == "dev"
Requires-Dist: ruff>=0.1.0; extra == "dev"
Provides-Extra: llm
Requires-Dist: litellm>=1.0.0; extra == "llm"
Requires-Dist: python-dotenv>=1.0.0; extra == "llm"
Requires-Dist: pyyaml>=6.0.0; extra == "llm"
Provides-Extra: all
Requires-Dist: reclapp[dev,llm]; extra == "all"
Dynamic: license-file
